src/__init__.py
src/allowed_values.py
src/api_client.py
src/large_lots.py
src/responses.py
src/submission.py
src/web_client.py
eds_api_client-0.0.1.dist-info/METADATA
eds_api_client-0.0.1.dist-info/WHEEL
eds_api_client-0.0.1.dist-info/licenses/LICENSE
eds_api_client-0.0.1.dist-info/RECORD
