Metadata-Version: 2.1
Name: eds_api_client
Version: 0.0.1
Summary: API client for Chicago Economic Disclosure Statements (EDS)
Project-URL: Homepage, https://github.com/datamade/eds-api-client
Project-URL: Bug Tracker, https://github.com/datamade/eds-api-client/issues
Author-email: DataMade <info@datamade.us>
License-File: LICENSE
Classifier: License :: OSI Approved :: MIT License
Classifier: Operating System :: OS Independent
Classifier: Programming Language :: Python :: 3
Requires-Python: >=3.7
Requires-Dist: lxml==4.9.2
Requires-Dist: scrapelib==2.1.0
